{"cameraMode":{"drawMode":0,"name":"Shaded","section":"Shading Mode"},"sceneLighting":true,"audioPlay":false,"sceneViewState":{"m_AlwaysRefresh":false,"showFog":true,"showSkybox":true,"showFlares":true,"showImageEffects":true,"showParticleSystems":true,"showVisualEffectGraphs":true,"m_FxEnabled":true},"in2DMode":false,"pivot":{"x":-0.935246467590332,"y":5.743400573730469,"z":5.812945365905762},"rotation":{"x":-0.141399085521698,"y":-0.2357371598482132,"z":0.03468993678689003,"w":-0.9608623385429382},"size":7.833794593811035,"orthographic":false}